CHANGES.txt
CONTRIBUTORS.txt
MANIFEST.in
README.txt
setup.cfg
setup.py
docs/HISTORY.txt
docs/INSTALL.txt
docs/LICENSE.GPL
docs/LICENSE.txt
xhostplus/__init__.py
xhostplus.videojs.egg-info/.PKG-INFO.swp
xhostplus.videojs.egg-info/PKG-INFO
xhostplus.videojs.egg-info/SOURCES.txt
xhostplus.videojs.egg-info/dependency_links.txt
xhostplus.videojs.egg-info/entry_points.txt
xhostplus.videojs.egg-info/namespace_packages.txt
xhostplus.videojs.egg-info/not-zip-safe
xhostplus.videojs.egg-info/paster_plugins.txt
xhostplus.videojs.egg-info/requires.txt
xhostplus.videojs.egg-info/top_level.txt
xhostplus/videojs/README.txt
xhostplus/videojs/__init__.py
xhostplus/videojs/config.py
xhostplus/videojs/configure.zcml
xhostplus/videojs/browser/__init__.py
xhostplus/videojs/browser/configure.zcml
xhostplus/videojs/browser/videoview.pt
xhostplus/videojs/browser/views.py
xhostplus/videojs/browser/images/video-bg.png
xhostplus/videojs/browser/javascripts/video.js
xhostplus/videojs/browser/stylesheets/video-js.css
xhostplus/videojs/browser/stylesheets/vim.css
xhostplus/videojs/content/__init__.py
xhostplus/videojs/content/configure.zcml
xhostplus/videojs/content/video.py
xhostplus/videojs/interfaces/__init__.py
xhostplus/videojs/interfaces/video.py
xhostplus/videojs/locales/xhostplus.videojs.pot
xhostplus/videojs/locales/de/LC_MESSAGES/xhostplus.videojs.mo
xhostplus/videojs/locales/de/LC_MESSAGES/xhostplus.videojs.po
xhostplus/videojs/locales/en/LC_MESSAGES/xhostplus.videojs.mo
xhostplus/videojs/locales/en/LC_MESSAGES/xhostplus.videojs.po
xhostplus/videojs/portlets/__init__.py
xhostplus/videojs/portlets/configure.zcml
xhostplus/videojs/profiles/default/browserlayer.xml
xhostplus/videojs/profiles/default/factorytool.xml
xhostplus/videojs/profiles/default/metadata.xml
xhostplus/videojs/profiles/default/portlets.xml
xhostplus/videojs/profiles/default/rolemap.xml
xhostplus/videojs/profiles/default/types.xml
xhostplus/videojs/profiles/default/types/Video.xml
xhostplus/videojs/tests/__init__.py
xhostplus/videojs/tests/base.py
xhostplus/videojs/tests/test_doctest.py