Metadata-Version: 1.1
Name: xhostplus.videojs
Version: 1.2.3
Summary: A javascript videoplayer with flash fallback
Home-page: http://www.xhostplus.at/de/services/plone-downlods
Author: Andreas Stocker
Author-email: andreas.stocker@xhostplus.at
License: GPL
Keywords: plone zope videojs html5 flash multimedia
Platform: UNKNOWN
Classifier: Framework :: Plone
Classifier: Intended Audience :: Developers
Classifier: Topic :: Software Development :: Libraries :: Python Modules
Classifier: License :: OSI Approved :: GNU General Public License (GPL)
